mlaflow/__init__.py
mlaflow/mlaflow.py
mlaflow-1.0.2.13.dist-info/licenses/LICENSE
mlaflow-1.0.2.13.dist-info/METADATA
mlaflow-1.0.2.13.dist-info/WHEEL
mlaflow-1.0.2.13.dist-info/top_level.txt
mlaflow-1.0.2.13.dist-info/RECORD
