Metadata-Version: 2.4
Name: mlaflow
Version: 1.0.2.13
Summary: A package for unsupervised and fully automatic processing of single-cell sequencing data throughout the entire workflow.
Author: jianing kang
Author-email: U202342138@xs.ustb.edu.cn
Keywords: python,mlaflow,MLAflow,single-cell,scRNA-seq,bioinformatics,machine learning
Classifier: Development Status :: 4 - Beta
Classifier: Intended Audience :: Developers
Classifier: Programming Language :: Python :: 3.6
Classifier: Programming Language :: Python :: 3.7
Classifier: Programming Language :: Python :: 3.8
Classifier: Programming Language :: Python :: 3.9
Classifier: Programming Language :: Python :: 3.10
Classifier: Programming Language :: Python :: 3.11
Classifier: Programming Language :: Python :: 3.12
Classifier: Operating System :: Microsoft :: Windows
Classifier: License :: OSI Approved :: MIT License
License-File: LICENSE
Requires-Dist: scanpy>=1.7.2
Requires-Dist: optuna>=2.8.0
Requires-Dist: cma>=3.0
Requires-Dist: umap-learn>=0.5.1
Dynamic: author
Dynamic: author-email
Dynamic: classifier
Dynamic: description
Dynamic: description-content-type
Dynamic: keywords
Dynamic: license-file
Dynamic: requires-dist
Dynamic: summary
